redcline/__init__.py
redcline/cli.py
redcline-0.1.dist-info/LICENSE
redcline-0.1.dist-info/METADATA
redcline-0.1.dist-info/WHEEL
redcline-0.1.dist-info/entry_points.txt
redcline-0.1.dist-info/top_level.txt
redcline-0.1.dist-info/RECORD
